schemachange/__init__.py
schemachange/cli.py
schemachange_hellofresh-3.5.4.dist-info/LICENSE
schemachange_hellofresh-3.5.4.dist-info/METADATA
schemachange_hellofresh-3.5.4.dist-info/NOTICE
schemachange_hellofresh-3.5.4.dist-info/WHEEL
schemachange_hellofresh-3.5.4.dist-info/entry_points.txt
schemachange_hellofresh-3.5.4.dist-info/top_level.txt
schemachange_hellofresh-3.5.4.dist-info/RECORD
