Metadata-Version: 2.1
Name: schemachange-hellofresh
Version: 3.5.4
Summary: A Database Change Management tool for Snowflake
Home-page: https://github.com/Snowflake-Labs/schemachange
Author: US OPS Analytics
Author-email: sca-automation@hellofresh.com
Classifier: Programming Language :: Python :: 3.7
Classifier: Programming Language :: Python :: 3.8
Classifier: Programming Language :: Python :: 3.9
Classifier: Operating System :: OS Independent
Requires-Python: >=3.7
License-File: LICENSE
License-File: NOTICE
Requires-Dist: snowflake-connector-python (~=2.8)
Requires-Dist: pandas (~=1.3)
Requires-Dist: pyyaml (==6.0)
Requires-Dist: jinja2 (~=3.0)
Provides-Extra: dev
Requires-Dist: pytest ; extra == 'dev'
